samples/__init__.py
samples/calculator.py
samples/test_calculator.py
invenio_et_probo-0.1.0.dist-info/METADATA
invenio_et_probo-0.1.0.dist-info/WHEEL
invenio_et_probo-0.1.0.dist-info/entry_points.txt
invenio_et_probo-0.1.0.dist-info/top_level.txt
invenio_et_probo-0.1.0.dist-info/RECORD
