Metadata-Version: 2.2
Name: invenio-et-probo
Version: 0.1.0
Summary: A GUI-based test runner for Python unit tests and integration tests
Author: Your Name
Author-email: Your Name <your.email@example.com>
License: MIT
Project-URL: Homepage, https://github.com/yourusername/invenio-et-probo
Project-URL: Repository, https://github.com/yourusername/invenio-et-probo.git
Project-URL: Changelog, https://github.com/yourusername/invenio-et-probo/blob/main/Docs/CHANGELOG.md
Classifier: Development Status :: 3 - Alpha
Classifier: Intended Audience :: Developers
Classifier: Topic :: Software Development :: Testing
Classifier: Programming Language :: Python :: 3.7
Classifier: Programming Language :: Python :: 3.8
Classifier: Programming Language :: Python :: 3.9
Classifier: Programming Language :: Python :: 3.10
Requires-Python: >=3.7
Requires-Dist: ttkbootstrap>=1.0.0
Dynamic: author
Dynamic: requires-python
